witsml21/__init__.py
witsml21/absolute_pressure.py
witsml21/absolute_pressure_interval.py
witsml21/absorbed_dose_measure.py
witsml21/absorbed_dose_measure_ext.py
witsml21/absorbed_dose_uom.py
witsml21/abstract2d_crs.py
witsml21/abstract2d_position.py
witsml21/abstract3d_position.py
witsml21/abstract_active_object.py
witsml21/abstract_activity_parameter.py
witsml21/abstract_boolean_array.py
witsml21/abstract_bottom_hole_temperature.py
witsml21/abstract_cartesian2d_position.py
witsml21/abstract_cement_job.py
witsml21/abstract_cement_stage.py
witsml21/abstract_compound_crs.py
witsml21/abstract_compound_position.py
witsml21/abstract_connection_type.py
witsml21/abstract_elevation.py
witsml21/abstract_event_extension.py
witsml21/abstract_floating_point_array.py
witsml21/abstract_geographic2d_crs.py
witsml21/abstract_graphical_information.py
witsml21/abstract_growing_object.py
witsml21/abstract_growing_object_part.py
witsml21/abstract_horizontal_coordinates.py
witsml21/abstract_integer_array.py
witsml21/abstract_interval.py
witsml21/abstract_item_wt_or_vol_per_unit.py
witsml21/abstract_md_growing_object.py
witsml21/abstract_md_growing_part.py
witsml21/abstract_md_interval_growing_part.py
witsml21/abstract_numeric_array.py
witsml21/abstract_object.py
witsml21/abstract_operating_range.py
witsml21/abstract_parameter_key.py
witsml21/abstract_position.py
witsml21/abstract_pressure_interval.py
witsml21/abstract_pressure_value.py
witsml21/abstract_projected_crs.py
witsml21/abstract_reference_point.py
witsml21/abstract_rotary_steerable_tool.py
witsml21/abstract_string_array.py
witsml21/abstract_temperature_pressure.py
witsml21/abstract_time_growing_object.py
witsml21/abstract_time_growing_part.py
witsml21/abstract_time_interval_growing_part.py
witsml21/abstract_tvd_interval.py
witsml21/abstract_value_array.py
witsml21/abstract_vertical_crs.py
witsml21/abstract_vertical_depth.py
witsml21/accelerometer_axis_combination.py
witsml21/acidize_frac_extension.py
witsml21-1.0.0.dist-info/LICENSE
witsml21-1.0.0.dist-info/WHEEL
witsml21-1.0.0.dist-info/METADATA
witsml21-1.0.0.dist-info/RECORD
